pyenergi/__init__.py
pyenergi/client.py
pyenergi/exceptions.py
pyenergi/schemas.py
pyenergi/test_client_authentication.py
pyenergi/test_client_zappi.py
pyenergi-0.0.1a2.dist-info/METADATA
pyenergi-0.0.1a2.dist-info/WHEEL
pyenergi-0.0.1a2.dist-info/licenses/LICENSE
pyenergi-0.0.1a2.dist-info/RECORD
