Metadata-Version: 2.3
Name: pyenergi
Version: 0.0.1a2
Summary: Python client for the myenergi API
Project-URL: Homepage, https://pyenergi.readthedocs.io
Project-URL: Documentation, https://pyenergi.readthedocs.io
Project-URL: Changelog, https://pyenergi.readthedocs.io/en/latest/CHANGELOG.html
Project-URL: Repository, https://github.com/KyeRussell/pyenergi
Project-URL: Issues, https://github.com/KyeRussell/pyenergi/issues
Author-email: Kye Russell <me@kye.id.au>
License:                     GNU AFFERO GENERAL PUBLIC LICENSE
License-File: LICENSE
Keywords: home automation,internet of things,iot,myenergi
Classifier: Development Status :: 1 - Planning
Classifier: License :: OSI Approved :: GNU Affero General Public License v3 or later (AGPLv3+)
Classifier: Natural Language :: English
Classifier: Topic :: Software Development
Requires-Python: >=3.11
Requires-Dist: httpx
Requires-Dist: pydantic<2
Requires-Dist: rich
Requires-Dist: typer
Provides-Extra: dev
Requires-Dist: build; extra == 'dev'
Requires-Dist: hatch; extra == 'dev'
Requires-Dist: mypy; extra == 'dev'
Requires-Dist: pre-commit; extra == 'dev'
Requires-Dist: pytest; extra == 'dev'
Requires-Dist: pytest-asyncio; extra == 'dev'
Requires-Dist: pytest-cov; extra == 'dev'
Requires-Dist: ruff; extra == 'dev'
Provides-Extra: docs
Requires-Dist: furo; extra == 'docs'
Requires-Dist: myst-parser; extra == 'docs'
Requires-Dist: sphinx; extra == 'docs'
Requires-Dist: sphinx-autobuild; extra == 'docs'
Requires-Dist: sphinx-autodoc-typehints; extra == 'docs'
